es/__init__.py
es/baseapi.py
es/basesqlalchemy.py
es/const.py
es/exceptions.py
es/elastic/__init__.py
es/elastic/api.py
es/elastic/sqlalchemy.py
es/opendistro/__init__.py
es/opendistro/api.py
es/opendistro/sqlalchemy.py
es/tests/__init__.py
es/tests/test_0_fixtures.py
es/tests/test_dbapi.py
es/tests/test_sqlalchemy.py
es/tests/fixtures/__init__.py
es/tests/fixtures/data1.json
es/tests/fixtures/data1_mappings.json
es/tests/fixtures/fixtures.py
es/tests/fixtures/flights.json
ct_elasticsearch_dbapi-0.2.12.dist-info/LICENSE.txt
ct_elasticsearch_dbapi-0.2.12.dist-info/METADATA
ct_elasticsearch_dbapi-0.2.12.dist-info/WHEEL
ct_elasticsearch_dbapi-0.2.12.dist-info/entry_points.txt
ct_elasticsearch_dbapi-0.2.12.dist-info/top_level.txt
ct_elasticsearch_dbapi-0.2.12.dist-info/RECORD
