Metadata-Version: 2.1
Name: ct-elasticsearch-dbapi
Version: 0.2.12
Summary: A DBAPI and SQLAlchemy dialect for Elasticsearch
Home-page: http://preset.io
Download-URL: https://github.com/preset-io/elasticsearch-dbapi/releases/tag/0.2.12
Author: Preset Inc.
Author-email: daniel@preset.io
License: Apache License, Version 2.0
Classifier: Programming Language :: Python :: 3.6
Classifier: Programming Language :: Python :: 3.7
Classifier: Programming Language :: Python :: 3.8
Classifier: Programming Language :: Python :: 3.9
License-File: LICENSE.txt
Requires-Dist: elasticsearch <7.14,>7
Requires-Dist: packaging >=21.0
Requires-Dist: sqlalchemy
Provides-Extra: opendistro
Requires-Dist: requests-aws4auth ; extra == 'opendistro'
Requires-Dist: boto3 ; extra == 'opendistro'
